ATRFileHandler/__init__.py
ATRFileHandler-0.1.1.dist-info/LICENSE
ATRFileHandler-0.1.1.dist-info/METADATA
ATRFileHandler-0.1.1.dist-info/WHEEL
ATRFileHandler-0.1.1.dist-info/top_level.txt
ATRFileHandler-0.1.1.dist-info/RECORD
