Metadata-Version: 2.1
Name: ATRFileHandler
Version: 0.1.1
Summary: Time handler for repetitive short-duration processes.
Home-page: https://github.com/manuelpepe/ATRFileHandler
Author: Manuel Pepe
Author-email: manuelpepe-dev@outlook.com.ar
License: UNKNOWN
Platform: UNKNOWN
